arbok/__init__.py
arbok/__main__.py
arbok/autosklearn.py
arbok/base.py
arbok/bench.py
arbok/out.py
arbok/param_preprocessor.py
arbok/param_preprocessor_new.py
arbok/preprocessing.py
arbok/tpot.py
arbok-0.1.21.dist-info/DESCRIPTION.rst
arbok-0.1.21.dist-info/METADATA
arbok-0.1.21.dist-info/RECORD
arbok-0.1.21.dist-info/WHEEL
arbok-0.1.21.dist-info/entry_points.txt
arbok-0.1.21.dist-info/metadata.json
arbok-0.1.21.dist-info/top_level.txt
