Metadata-Version: 2.0
Name: arbok
Version: 0.1.21
Summary: A wrapper toolbox that provides compatibility layers between TPOT and Auto-Sklearn and OpenML
Home-page: https://github.com/Yatoom/arbok
Author: Jeroen van Hoof
Author-email: jeroen@jeroenvanhoof.nl
License: UNKNOWN
Platform: UNKNOWN
Requires-Dist: sklearn
Requires-Dist: auto-sklearn
Requires-Dist: tpot
Requires-Dist: numpy
Requires-Dist: click
Requires-Dist: Cython
Requires-Dist: oslo.concurrency
